{
    "0":["$(function(..){};", "即時関数"],
    "1":["$(#id).text('text');", "テキスト表示"],
    "2":["$(#id).html('html')+", "HTML表示"],
    "3":["$(#id).click(function(..){});", "clickされたらfunction実行"],
    "4":["$('input[name=like]:checked()).val();", ""],
    "5":["", ""],
    "6":["", ""],
    "7":["", ""],
    "8":["", ""],
    "9":["", ""],
    "10":["", ""],
    "11":["", ""],
    "12":["", ""],
    "13":["", ""],
    "14":["", ""],
    "15":["", ""],
    "16":["", ""],
    "17":["", ""],
    "18":["", ""],
    "19":["", ""],
    "20":["", ""],
    "21":["", ""],
    "22":["", ""],
    "23":["", ""],
    "24":["", ""],
    "25":["", ""],
    "26":["", ""],
    "27":["", ""],
    "28":["", ""],
    "29":["", ""]
    }
    